cutoop/__init__.py
cutoop/align.py
cutoop/bbox.py
cutoop/data_loader.py
cutoop/data_types.py
cutoop/eval_utils.py
cutoop/image_meta.py
cutoop/log.py
cutoop/obj_meta.py
cutoop/rotation.py
cutoop/transform.py
cutoop/utils.py
cutoop/iou/__init__.py
cutoop/iou/box.py
cutoop/iou/iou.py
cutoop-0.1.0.dist-info/LICENSE.rst
cutoop-0.1.0.dist-info/METADATA
cutoop-0.1.0.dist-info/WHEEL
cutoop-0.1.0.dist-info/top_level.txt
cutoop-0.1.0.dist-info/RECORD
