Metadata-Version: 2.1
Name: cutoop
Version: 0.1.0
Summary: Common UTilities for Omni6DPose
Author: Weiyao Huang
Author-email: jy.cat@qq.com
License: MIT
Keywords: post_estimation
Classifier: Programming Language :: Python :: 3
Requires-Python: >=3.7
License-File: LICENSE.rst
Requires-Dist: numpy >=1.21
Requires-Dist: ipdb >=0.13.9
Requires-Dist: matplotlib >=3.5
Requires-Dist: opencv-python >=4.8.0.76
Requires-Dist: Pillow >=8.3
Requires-Dist: rich >=13.7.0
Requires-Dist: scipy >=1.7.3
Requires-Dist: tqdm >=4.65.2
Requires-Dist: typing-extensions >=4.7.1
Requires-Dist: importlib-metadata ; python_version < "3.10"
